{
  "conditions": [
    {
      "condition": "mod_loaded",
      "mod_id": "ensorcellation"
    },
    {
      "condition": "cofh_enabled",
      "enchantment": "ensorcellation:angler"
    }
  ],
  "cost": 6,
  "ingredients": [
    {
      "count": 1,
      "ingredient": {
        "item": "minecraft:golden_pickaxe"
      }
    },
    {
      "count": 48,
      "ingredient": {
        "tag": "forge:gems/lapis"
      }
    },
    {
      "count": 1,
      "ingredient": {
        "item": "minecraft:heart_of_the_sea"
      }
    }
  ],
  "result": {
    "enchantment": "ensorcellation:angler",
    "level": 2
  }
}